{
  "id": "disasters-week2-cagatay-468400_chunk_2.ann.tsvx",
  "text": "K\u00fctahya ve \u00e7evresinde etkin olan di\u011fer depremler ise 1928 Emet 6.2 , 1944 \u015eaphane 6.2 , _ 1970 Gediz 7.2 _ , 1970 \u00c7avdarhisar 5.9 ve 2011 Simav 5 , 9 bu depremler b\u00f6lgede a\u011f\u0131r hasar vermi\u015ftir .\t\t\t\t",
  "event": {
    "T0": {
      "id": "T0",
      "text": "depremler",
      "label": "EVENT",
      "char_index": 39,
      "sid": 0,
      "tid": [
        6,
        7
      ]
    },
    "T1": {
      "id": "T1",
      "text": "depremler",
      "label": "EVENT",
      "char_index": 153,
      "sid": 0,
      "tid": [
        32,
        33
      ]
    }
  },
  "relation": {},
  "sentence": [
    [
      "K\u00fctahya",
      "ve",
      "\u00e7evresinde",
      "etkin",
      "olan",
      "di\u011fer",
      "depremler",
      "ise",
      "1928",
      "Emet",
      "6.2",
      ",",
      "1944",
      "\u015eaphane",
      "6.2",
      ",",
      "_",
      "1970",
      "Gediz",
      "7.2",
      "_",
      ",",
      "1970",
      "\u00c7avdarhisar",
      "5.9",
      "ve",
      "2011",
      "Simav",
      "5",
      ",",
      "9",
      "bu",
      "depremler",
      "b\u00f6lgede",
      "a\u011f\u0131r",
      "hasar",
      "vermi\u015ftir",
      "."
    ]
  ],
  "deprel": [
    [
      [
        0,
        0
      ],
      [
        0,
        4
      ],
      "obl"
    ],
    [
      [
        0,
        1
      ],
      [
        0,
        2
      ],
      "cc"
    ],
    [
      [
        0,
        2
      ],
      [
        0,
        0
      ],
      "conj"
    ],
    [
      [
        0,
        3
      ],
      [
        0,
        4
      ],
      "amod"
    ],
    [
      [
        0,
        4
      ],
      [
        0,
        6
      ],
      "acl"
    ],
    [
      [
        0,
        5
      ],
      [
        0,
        6
      ],
      "amod"
    ],
    [
      [
        0,
        6
      ],
      [
        0,
        35
      ],
      "nsubj"
    ],
    [
      [
        0,
        7
      ],
      [
        0,
        6
      ],
      "discourse"
    ],
    [
      [
        0,
        8
      ],
      [
        0,
        9
      ],
      "nmod"
    ],
    [
      [
        0,
        9
      ],
      [
        0,
        35
      ],
      "nmod"
    ],
    [
      [
        0,
        10
      ],
      [
        0,
        9
      ],
      "flat"
    ],
    [
      [
        0,
        11
      ],
      [
        0,
        13
      ],
      "punct"
    ],
    [
      [
        0,
        12
      ],
      [
        0,
        8
      ],
      "conj"
    ],
    [
      [
        0,
        13
      ],
      [
        0,
        9
      ],
      "conj"
    ],
    [
      [
        0,
        14
      ],
      [
        0,
        13
      ],
      "flat"
    ],
    [
      [
        0,
        15
      ],
      [
        0,
        18
      ],
      "punct"
    ],
    [
      [
        0,
        16
      ],
      [
        0,
        18
      ],
      "punct"
    ],
    [
      [
        0,
        17
      ],
      [
        0,
        8
      ],
      "conj"
    ],
    [
      [
        0,
        18
      ],
      [
        0,
        9
      ],
      "conj"
    ],
    [
      [
        0,
        19
      ],
      [
        0,
        18
      ],
      "flat"
    ],
    [
      [
        0,
        20
      ],
      [
        0,
        18
      ],
      "punct"
    ],
    [
      [
        0,
        21
      ],
      [
        0,
        24
      ],
      "punct"
    ],
    [
      [
        0,
        22
      ],
      [
        0,
        9
      ],
      "conj"
    ],
    [
      [
        0,
        23
      ],
      [
        0,
        9
      ],
      "conj"
    ],
    [
      [
        0,
        24
      ],
      [
        0,
        9
      ],
      "conj"
    ],
    [
      [
        0,
        25
      ],
      [
        0,
        27
      ],
      "cc"
    ],
    [
      [
        0,
        26
      ],
      [
        0,
        9
      ],
      "conj"
    ],
    [
      [
        0,
        27
      ],
      [
        0,
        9
      ],
      "conj"
    ],
    [
      [
        0,
        28
      ],
      [
        0,
        27
      ],
      "flat"
    ],
    [
      [
        0,
        29
      ],
      [
        0,
        27
      ],
      "punct"
    ],
    [
      [
        0,
        30
      ],
      [
        0,
        26
      ],
      "compound"
    ],
    [
      [
        0,
        31
      ],
      [
        0,
        32
      ],
      "det"
    ],
    [
      [
        0,
        32
      ],
      [
        0,
        35
      ],
      "nsubj"
    ],
    [
      [
        0,
        33
      ],
      [
        0,
        35
      ],
      "nmod"
    ],
    [
      [
        0,
        34
      ],
      [
        0,
        35
      ],
      "amod"
    ],
    [
      [
        0,
        35
      ],
      [
        0,
        -1
      ],
      "root"
    ],
    [
      [
        0,
        36
      ],
      [
        0,
        35
      ],
      "compound"
    ],
    [
      [
        0,
        37
      ],
      [
        0,
        35
      ],
      "punct"
    ]
  ]
}