{
  "id": "economic_crisis-week2-cagatay-2948193_chunk_0.ann.tsvx",
  "text": "HEINKEL HD 38 , 1920'lerin sonunda Almanya'da geli\u015ftirilen bir sava\u015f u\u00e7a\u011f\u0131yd\u0131 .\tLipetsk'teki gizli e\u011fitim \u00fcss\u00fcnde kullan\u0131lmak \u00fczere Reichswehr'ce de\u011ferlendirilen ve reddedilen Heinkel HD 37'nin s\u00fcr\u00fcm\u00fc olan , a\u015famal\u0131 kanatlara sahip , tek b\u00f6lmeli , \u00e7ift kanatl\u0131 u\u00e7akt\u0131 .\tKategori : Heinkel Kategori : Heinkel u\u00e7aklar\u0131 Kategori : Weimar Cumhuriyeti u\u00e7aklar\u0131 Kategori : Avc\u0131 u\u00e7aklar\u0131\t\t",
  "event": {
    "T1": {
      "id": "T1",
      "text": "de\u011ferlendirilen",
      "label": "EVENT",
      "char_index": 146,
      "sid": 1,
      "tid": [
        7,
        8
      ]
    },
    "T2": {
      "id": "T2",
      "text": "reddedilen",
      "label": "EVENT",
      "char_index": 165,
      "sid": 1,
      "tid": [
        9,
        10
      ]
    },
    "T3": {
      "id": "T3",
      "text": "geli\u015ftirilen",
      "label": "EVENT",
      "char_index": 46,
      "sid": 0,
      "tid": [
        7,
        8
      ]
    }
  },
  "relation": {
    "T3-T1": "CauseEffect",
    "T1-T3": "EffectCause",
    "T1-T2": "CauseEffect",
    "T2-T1": "EffectCause",
    "T2-T3": "NoRel"
  },
  "sentence": [
    [
      "HEINKEL",
      "HD",
      "38",
      ",",
      "1920'lerin",
      "sonunda",
      "Almanya'da",
      "geli\u015ftirilen",
      "bir",
      "sava\u015f",
      "u\u00e7a\u011f\u0131yd\u0131",
      "."
    ],
    [
      "Lipetsk'teki",
      "gizli",
      "e\u011fitim",
      "\u00fcss\u00fcnde",
      "kullan\u0131lmak",
      "\u00fczere",
      "Reichswehr'ce",
      "de\u011ferlendirilen",
      "ve",
      "reddedilen",
      "Heinkel",
      "HD",
      "37'nin",
      "s\u00fcr\u00fcm\u00fc",
      "olan",
      ",",
      "a\u015famal\u0131",
      "kanatlara",
      "sahip",
      ",",
      "tek",
      "b\u00f6lmeli",
      ",",
      "\u00e7ift",
      "kanatl\u0131",
      "u\u00e7akt\u0131",
      "."
    ],
    [
      "Kategori",
      ":",
      "Heinkel",
      "Kategori",
      ":",
      "Heinkel",
      "u\u00e7aklar\u0131",
      "Kategori",
      ":",
      "Weimar",
      "Cumhuriyeti",
      "u\u00e7aklar\u0131",
      "Kategori",
      ":",
      "Avc\u0131",
      "u\u00e7aklar\u0131"
    ]
  ],
  "deprel": [
    [
      [
        0,
        0
      ],
      [
        0,
        10
      ],
      "nsubj"
    ],
    [
      [
        0,
        1
      ],
      [
        0,
        0
      ],
      "compound"
    ],
    [
      [
        0,
        2
      ],
      [
        0,
        0
      ],
      "compound"
    ],
    [
      [
        0,
        3
      ],
      [
        0,
        10
      ],
      "punct"
    ],
    [
      [
        0,
        4
      ],
      [
        0,
        5
      ],
      "nmod:poss"
    ],
    [
      [
        0,
        5
      ],
      [
        0,
        7
      ],
      "amod"
    ],
    [
      [
        0,
        6
      ],
      [
        0,
        7
      ],
      "obl"
    ],
    [
      [
        0,
        7
      ],
      [
        0,
        10
      ],
      "acl"
    ],
    [
      [
        0,
        8
      ],
      [
        0,
        10
      ],
      "det"
    ],
    [
      [
        0,
        9
      ],
      [
        0,
        10
      ],
      "nmod:poss"
    ],
    [
      [
        0,
        10
      ],
      [
        0,
        -1
      ],
      "root"
    ],
    [
      [
        0,
        11
      ],
      [
        0,
        10
      ],
      "punct"
    ],
    [
      [
        1,
        0
      ],
      [
        1,
        2
      ],
      "nmod"
    ],
    [
      [
        1,
        1
      ],
      [
        1,
        2
      ],
      "amod"
    ],
    [
      [
        1,
        2
      ],
      [
        1,
        3
      ],
      "nmod:poss"
    ],
    [
      [
        1,
        3
      ],
      [
        1,
        4
      ],
      "obl"
    ],
    [
      [
        1,
        4
      ],
      [
        1,
        7
      ],
      "nmod"
    ],
    [
      [
        1,
        5
      ],
      [
        1,
        4
      ],
      "case"
    ],
    [
      [
        1,
        6
      ],
      [
        1,
        7
      ],
      "obl"
    ],
    [
      [
        1,
        7
      ],
      [
        1,
        10
      ],
      "acl"
    ],
    [
      [
        1,
        8
      ],
      [
        1,
        9
      ],
      "cc"
    ],
    [
      [
        1,
        9
      ],
      [
        1,
        7
      ],
      "conj"
    ],
    [
      [
        1,
        10
      ],
      [
        1,
        13
      ],
      "nmod:poss"
    ],
    [
      [
        1,
        11
      ],
      [
        1,
        10
      ],
      "compound"
    ],
    [
      [
        1,
        12
      ],
      [
        1,
        13
      ],
      "nmod:poss"
    ],
    [
      [
        1,
        13
      ],
      [
        1,
        14
      ],
      "nsubj"
    ],
    [
      [
        1,
        14
      ],
      [
        1,
        25
      ],
      "acl"
    ],
    [
      [
        1,
        15
      ],
      [
        1,
        14
      ],
      "punct"
    ],
    [
      [
        1,
        16
      ],
      [
        1,
        17
      ],
      "amod"
    ],
    [
      [
        1,
        17
      ],
      [
        1,
        18
      ],
      "nmod"
    ],
    [
      [
        1,
        18
      ],
      [
        1,
        25
      ],
      "nmod"
    ],
    [
      [
        1,
        19
      ],
      [
        1,
        24
      ],
      "punct"
    ],
    [
      [
        1,
        20
      ],
      [
        1,
        21
      ],
      "amod"
    ],
    [
      [
        1,
        21
      ],
      [
        1,
        25
      ],
      "amod"
    ],
    [
      [
        1,
        22
      ],
      [
        1,
        24
      ],
      "punct"
    ],
    [
      [
        1,
        23
      ],
      [
        1,
        24
      ],
      "amod"
    ],
    [
      [
        1,
        24
      ],
      [
        1,
        21
      ],
      "conj"
    ],
    [
      [
        1,
        25
      ],
      [
        1,
        -1
      ],
      "root"
    ],
    [
      [
        1,
        26
      ],
      [
        1,
        25
      ],
      "punct"
    ],
    [
      [
        2,
        0
      ],
      [
        2,
        -1
      ],
      "root"
    ],
    [
      [
        2,
        1
      ],
      [
        2,
        2
      ],
      "punct"
    ],
    [
      [
        2,
        2
      ],
      [
        2,
        0
      ],
      "compound"
    ],
    [
      [
        2,
        3
      ],
      [
        2,
        0
      ],
      "conj"
    ],
    [
      [
        2,
        4
      ],
      [
        2,
        3
      ],
      "punct"
    ],
    [
      [
        2,
        5
      ],
      [
        2,
        6
      ],
      "nmod:poss"
    ],
    [
      [
        2,
        6
      ],
      [
        2,
        3
      ],
      "compound"
    ],
    [
      [
        2,
        7
      ],
      [
        2,
        0
      ],
      "conj"
    ],
    [
      [
        2,
        8
      ],
      [
        2,
        7
      ],
      "punct"
    ],
    [
      [
        2,
        9
      ],
      [
        2,
        7
      ],
      "nmod"
    ],
    [
      [
        2,
        10
      ],
      [
        2,
        9
      ],
      "flat"
    ],
    [
      [
        2,
        11
      ],
      [
        2,
        9
      ],
      "compound"
    ],
    [
      [
        2,
        12
      ],
      [
        2,
        0
      ],
      "conj"
    ],
    [
      [
        2,
        13
      ],
      [
        2,
        12
      ],
      "punct"
    ],
    [
      [
        2,
        14
      ],
      [
        2,
        15
      ],
      "nmod:poss"
    ],
    [
      [
        2,
        15
      ],
      [
        2,
        0
      ],
      "conj"
    ]
  ]
}