{
  "id": "epidemics-week2-laila-1060786_chunk_2.ann.tsvx",
  "text": "Som ung hj\u00e6lpel\u00e6ge oplevede han epidemien omkring Faxe .\tEmil Hornemann oplevede som ung epidemien p\u00e5 f\u00f8rste h\u00e5nd , da han blev sendt ud som hj\u00e6lpel\u00e6ge og arbejdede fra Turebyholm ved Faxe .\tHan skrev senere i 1800-tallet at epidemien var \" Den betydeligste og alvorligste epidemi , der i dette \u00e5rhundrede har hjems\u00f8gt vort f\u00f8deland \" .\tDet var efter at han ogs\u00e5 havde oplevet koleraepidemien i 1853 .\tFra Sor\u00f8 oplevede digteren B.S. Ingemann ogs\u00e5 epidemien .",
  "event": {
    "T0": {
      "id": "T0",
      "text": "oplevede",
      "label": "EVENT",
      "char_index": 19,
      "sid": 0,
      "tid": [
        3,
        4
      ]
    },
    "T1": {
      "id": "T1",
      "text": "epidemien",
      "label": "EVENT",
      "char_index": 32,
      "sid": 0,
      "tid": [
        5,
        6
      ]
    },
    "T10": {
      "id": "T10",
      "text": "epidemien",
      "label": "EVENT",
      "char_index": 448,
      "sid": 4,
      "tid": [
        7,
        8
      ]
    },
    "T2": {
      "id": "T2",
      "text": "oplevede",
      "label": "EVENT",
      "char_index": 72,
      "sid": 1,
      "tid": [
        2,
        3
      ]
    },
    "T3": {
      "id": "T3",
      "text": "epidemien",
      "label": "EVENT",
      "char_index": 89,
      "sid": 1,
      "tid": [
        5,
        6
      ]
    },
    "T4": {
      "id": "T4",
      "text": "arbejdede",
      "label": "EVENT",
      "char_index": 155,
      "sid": 1,
      "tid": [
        18,
        19
      ]
    },
    "T5": {
      "id": "T5",
      "text": "skrev",
      "label": "EVENT",
      "char_index": 195,
      "sid": 2,
      "tid": [
        1,
        2
      ]
    },
    "T6": {
      "id": "T6",
      "text": "epidemi",
      "label": "EVENT",
      "char_index": 273,
      "sid": 2,
      "tid": [
        13,
        14
      ]
    },
    "T7": {
      "id": "T7",
      "text": "hjems\u00f8gt",
      "label": "EVENT",
      "char_index": 310,
      "sid": 2,
      "tid": [
        20,
        21
      ]
    },
    "T8": {
      "id": "T8",
      "text": "koleraepidemien",
      "label": "EVENT",
      "char_index": 377,
      "sid": 3,
      "tid": [
        8,
        9
      ]
    },
    "T9": {
      "id": "T9",
      "text": "oplevede",
      "label": "EVENT",
      "char_index": 411,
      "sid": 4,
      "tid": [
        2,
        3
      ]
    }
  },
  "relation": {
    "T4-T2": "CauseEffect",
    "T2-T4": "EffectCause",
    "T6-T5": "CauseEffect",
    "T5-T6": "EffectCause",
    "T2-T5": "CauseEffect",
    "T5-T2": "EffectCause",
    "T0-T5": "CauseEffect",
    "T5-T0": "EffectCause",
    "T10-T2": "NoRel",
    "T10-T9": "NoRel",
    "T2-T7": "NoRel",
    "T4-T0": "NoRel",
    "T5-T3": "NoRel",
    "T6-T1": "NoRel",
    "T6-T3": "NoRel",
    "T6-T7": "NoRel",
    "T7-T3": "NoRel",
    "T7-T8": "NoRel",
    "T9-T5": "NoRel"
  },
  "sentence": [
    [
      "Som",
      "ung",
      "hj\u00e6lpel\u00e6ge",
      "oplevede",
      "han",
      "epidemien",
      "omkring",
      "Faxe",
      "."
    ],
    [
      "Emil",
      "Hornemann",
      "oplevede",
      "som",
      "ung",
      "epidemien",
      "p\u00e5",
      "f\u00f8rste",
      "h\u00e5nd",
      ",",
      "da",
      "han",
      "blev",
      "sendt",
      "ud",
      "som",
      "hj\u00e6lpel\u00e6ge",
      "og",
      "arbejdede",
      "fra",
      "Turebyholm",
      "ved",
      "Faxe",
      "."
    ],
    [
      "Han",
      "skrev",
      "senere",
      "i",
      "1800-tallet",
      "at",
      "epidemien",
      "var",
      "\"",
      "Den",
      "betydeligste",
      "og",
      "alvorligste",
      "epidemi",
      ",",
      "der",
      "i",
      "dette",
      "\u00e5rhundrede",
      "har",
      "hjems\u00f8gt",
      "vort",
      "f\u00f8deland",
      "\"",
      "."
    ],
    [
      "Det",
      "var",
      "efter",
      "at",
      "han",
      "ogs\u00e5",
      "havde",
      "oplevet",
      "koleraepidemien",
      "i",
      "1853",
      "."
    ],
    [
      "Fra",
      "Sor\u00f8",
      "oplevede",
      "digteren",
      "B.S.",
      "Ingemann",
      "ogs\u00e5",
      "epidemien",
      "."
    ]
  ],
  "deprel": [
    [
      [
        0,
        0
      ],
      [
        0,
        2
      ],
      "case"
    ],
    [
      [
        0,
        1
      ],
      [
        0,
        2
      ],
      "amod"
    ],
    [
      [
        0,
        2
      ],
      [
        0,
        3
      ],
      "obl"
    ],
    [
      [
        0,
        3
      ],
      [
        0,
        -1
      ],
      "root"
    ],
    [
      [
        0,
        4
      ],
      [
        0,
        3
      ],
      "nsubj"
    ],
    [
      [
        0,
        5
      ],
      [
        0,
        3
      ],
      "obj"
    ],
    [
      [
        0,
        6
      ],
      [
        0,
        7
      ],
      "case"
    ],
    [
      [
        0,
        7
      ],
      [
        0,
        5
      ],
      "nmod"
    ],
    [
      [
        0,
        8
      ],
      [
        0,
        3
      ],
      "punct"
    ],
    [
      [
        1,
        0
      ],
      [
        1,
        2
      ],
      "nsubj"
    ],
    [
      [
        1,
        1
      ],
      [
        1,
        0
      ],
      "flat"
    ],
    [
      [
        1,
        2
      ],
      [
        1,
        -1
      ],
      "root"
    ],
    [
      [
        1,
        3
      ],
      [
        1,
        4
      ],
      "case"
    ],
    [
      [
        1,
        4
      ],
      [
        1,
        2
      ],
      "amod"
    ],
    [
      [
        1,
        5
      ],
      [
        1,
        2
      ],
      "obj"
    ],
    [
      [
        1,
        6
      ],
      [
        1,
        8
      ],
      "case"
    ],
    [
      [
        1,
        7
      ],
      [
        1,
        8
      ],
      "amod"
    ],
    [
      [
        1,
        8
      ],
      [
        1,
        2
      ],
      "obl"
    ],
    [
      [
        1,
        9
      ],
      [
        1,
        2
      ],
      "punct"
    ],
    [
      [
        1,
        10
      ],
      [
        1,
        13
      ],
      "mark"
    ],
    [
      [
        1,
        11
      ],
      [
        1,
        13
      ],
      "nsubj"
    ],
    [
      [
        1,
        12
      ],
      [
        1,
        13
      ],
      "aux"
    ],
    [
      [
        1,
        13
      ],
      [
        1,
        2
      ],
      "advmod"
    ],
    [
      [
        1,
        14
      ],
      [
        1,
        13
      ],
      "obl:loc"
    ],
    [
      [
        1,
        15
      ],
      [
        1,
        16
      ],
      "case"
    ],
    [
      [
        1,
        16
      ],
      [
        1,
        14
      ],
      "obl"
    ],
    [
      [
        1,
        17
      ],
      [
        1,
        18
      ],
      "cc"
    ],
    [
      [
        1,
        18
      ],
      [
        1,
        13
      ],
      "conj"
    ],
    [
      [
        1,
        19
      ],
      [
        1,
        20
      ],
      "case"
    ],
    [
      [
        1,
        20
      ],
      [
        1,
        18
      ],
      "obl"
    ],
    [
      [
        1,
        21
      ],
      [
        1,
        22
      ],
      "case"
    ],
    [
      [
        1,
        22
      ],
      [
        1,
        20
      ],
      "nmod"
    ],
    [
      [
        1,
        23
      ],
      [
        1,
        2
      ],
      "punct"
    ],
    [
      [
        2,
        0
      ],
      [
        2,
        1
      ],
      "nsubj"
    ],
    [
      [
        2,
        1
      ],
      [
        2,
        -1
      ],
      "root"
    ],
    [
      [
        2,
        2
      ],
      [
        2,
        1
      ],
      "advmod"
    ],
    [
      [
        2,
        3
      ],
      [
        2,
        4
      ],
      "case"
    ],
    [
      [
        2,
        4
      ],
      [
        2,
        2
      ],
      "obl"
    ],
    [
      [
        2,
        5
      ],
      [
        2,
        13
      ],
      "mark"
    ],
    [
      [
        2,
        6
      ],
      [
        2,
        13
      ],
      "nsubj"
    ],
    [
      [
        2,
        7
      ],
      [
        2,
        13
      ],
      "cop"
    ],
    [
      [
        2,
        8
      ],
      [
        2,
        13
      ],
      "punct"
    ],
    [
      [
        2,
        9
      ],
      [
        2,
        13
      ],
      "det"
    ],
    [
      [
        2,
        10
      ],
      [
        2,
        13
      ],
      "amod"
    ],
    [
      [
        2,
        11
      ],
      [
        2,
        12
      ],
      "cc"
    ],
    [
      [
        2,
        12
      ],
      [
        2,
        10
      ],
      "conj"
    ],
    [
      [
        2,
        13
      ],
      [
        2,
        1
      ],
      "ccomp"
    ],
    [
      [
        2,
        14
      ],
      [
        2,
        13
      ],
      "punct"
    ],
    [
      [
        2,
        15
      ],
      [
        2,
        20
      ],
      "nsubj"
    ],
    [
      [
        2,
        16
      ],
      [
        2,
        18
      ],
      "case"
    ],
    [
      [
        2,
        17
      ],
      [
        2,
        18
      ],
      "det"
    ],
    [
      [
        2,
        18
      ],
      [
        2,
        20
      ],
      "obl"
    ],
    [
      [
        2,
        19
      ],
      [
        2,
        20
      ],
      "aux"
    ],
    [
      [
        2,
        20
      ],
      [
        2,
        13
      ],
      "acl:relcl"
    ],
    [
      [
        2,
        21
      ],
      [
        2,
        22
      ],
      "det"
    ],
    [
      [
        2,
        22
      ],
      [
        2,
        20
      ],
      "obj"
    ],
    [
      [
        2,
        23
      ],
      [
        2,
        13
      ],
      "punct"
    ],
    [
      [
        2,
        24
      ],
      [
        2,
        1
      ],
      "punct"
    ],
    [
      [
        3,
        0
      ],
      [
        3,
        1
      ],
      "nsubj"
    ],
    [
      [
        3,
        1
      ],
      [
        3,
        -1
      ],
      "root"
    ],
    [
      [
        3,
        2
      ],
      [
        3,
        7
      ],
      "mark"
    ],
    [
      [
        3,
        3
      ],
      [
        3,
        7
      ],
      "mark"
    ],
    [
      [
        3,
        4
      ],
      [
        3,
        7
      ],
      "nsubj"
    ],
    [
      [
        3,
        5
      ],
      [
        3,
        7
      ],
      "advmod"
    ],
    [
      [
        3,
        6
      ],
      [
        3,
        7
      ],
      "aux"
    ],
    [
      [
        3,
        7
      ],
      [
        3,
        1
      ],
      "advmod"
    ],
    [
      [
        3,
        8
      ],
      [
        3,
        7
      ],
      "obj"
    ],
    [
      [
        3,
        9
      ],
      [
        3,
        10
      ],
      "case"
    ],
    [
      [
        3,
        10
      ],
      [
        3,
        7
      ],
      "nummod"
    ],
    [
      [
        3,
        11
      ],
      [
        3,
        1
      ],
      "punct"
    ],
    [
      [
        4,
        0
      ],
      [
        4,
        1
      ],
      "case"
    ],
    [
      [
        4,
        1
      ],
      [
        4,
        2
      ],
      "obl"
    ],
    [
      [
        4,
        2
      ],
      [
        4,
        -1
      ],
      "root"
    ],
    [
      [
        4,
        3
      ],
      [
        4,
        2
      ],
      "nsubj"
    ],
    [
      [
        4,
        4
      ],
      [
        4,
        3
      ],
      "appos"
    ],
    [
      [
        4,
        5
      ],
      [
        4,
        4
      ],
      "flat"
    ],
    [
      [
        4,
        6
      ],
      [
        4,
        2
      ],
      "advmod"
    ],
    [
      [
        4,
        7
      ],
      [
        4,
        2
      ],
      "obj"
    ],
    [
      [
        4,
        8
      ],
      [
        4,
        2
      ],
      "punct"
    ]
  ]
}