{
  "id": "railway_accidents-week4-fiona-5873267_chunk_2.ann.tsvx",
  "text": "Dos de ellos se produjeron en la estaci\u00f3n Once .\tEl primer siniestro se produjo el 22 de febrero de 2012 , provocando la muerte de 51 personas y lesiones a 702 personas .\tEl segundo se produjo el 13 de junio de 2013 , provocando la muerte de 3 personas y lesiones a 315 personas .\tEl tercero se produjo el 19 de octubre de 2013 , provocando lesiones a 105 personas .\t",
  "event": {
    "T0": {
      "id": "T0",
      "text": "produjeron",
      "label": "EVENT",
      "char_index": 16,
      "sid": 0,
      "tid": [
        4,
        5
      ]
    },
    "T1": {
      "id": "T1",
      "text": "siniestro",
      "label": "EVENT",
      "char_index": 59,
      "sid": 1,
      "tid": [
        2,
        3
      ]
    },
    "T2": {
      "id": "T2",
      "text": "produjo",
      "label": "EVENT",
      "char_index": 72,
      "sid": 1,
      "tid": [
        4,
        5
      ]
    },
    "T3": {
      "id": "T3",
      "text": "provocando",
      "label": "EVENT",
      "char_index": 107,
      "sid": 1,
      "tid": [
        12,
        13
      ]
    },
    "T4": {
      "id": "T4",
      "text": "muerte",
      "label": "EVENT",
      "char_index": 121,
      "sid": 1,
      "tid": [
        14,
        15
      ]
    },
    "T5": {
      "id": "T5",
      "text": "lesiones",
      "label": "EVENT",
      "char_index": 145,
      "sid": 1,
      "tid": [
        19,
        20
      ]
    },
    "T6": {
      "id": "T6",
      "text": "produjo",
      "label": "EVENT",
      "char_index": 185,
      "sid": 2,
      "tid": [
        3,
        4
      ]
    },
    "T7": {
      "id": "T7",
      "text": "provocando",
      "label": "EVENT",
      "char_index": 218,
      "sid": 2,
      "tid": [
        11,
        12
      ]
    },
    "T8": {
      "id": "T8",
      "text": "muerte",
      "label": "EVENT",
      "char_index": 232,
      "sid": 2,
      "tid": [
        13,
        14
      ]
    },
    "T9": {
      "id": "T9",
      "text": "lesiones",
      "label": "EVENT",
      "char_index": 255,
      "sid": 2,
      "tid": [
        18,
        19
      ]
    },
    "T10": {
      "id": "T10",
      "text": "tercero",
      "label": "EVENT",
      "char_index": 284,
      "sid": 3,
      "tid": [
        1,
        2
      ]
    },
    "T11": {
      "id": "T11",
      "text": "produjo",
      "label": "EVENT",
      "char_index": 295,
      "sid": 3,
      "tid": [
        3,
        4
      ]
    },
    "T12": {
      "id": "T12",
      "text": "lesiones",
      "label": "EVENT",
      "char_index": 341,
      "sid": 3,
      "tid": [
        12,
        13
      ]
    }
  },
  "relation": {
    "T1-T4": "CauseEffect",
    "T4-T1": "EffectCause",
    "T1-T5": "CauseEffect",
    "T5-T1": "EffectCause",
    "T0-T11": "NoRel",
    "T2-T7": "NoRel",
    "T2-T9": "NoRel",
    "T3-T4": "NoRel",
    "T4-T5": "NoRel",
    "T4-T8": "NoRel",
    "T5-T11": "NoRel",
    "T5-T7": "NoRel",
    "T5-T8": "NoRel",
    "T6-T1": "NoRel",
    "T6-T10": "NoRel",
    "T6-T9": "NoRel",
    "T7-T9": "NoRel",
    "T8-T11": "NoRel",
    "T8-T12": "NoRel",
    "T8-T5": "NoRel"
  },
  "sentence": [
    [
      "Dos",
      "de",
      "ellos",
      "se",
      "produjeron",
      "en",
      "la",
      "estaci\u00f3n",
      "Once",
      "."
    ],
    [
      "El",
      "primer",
      "siniestro",
      "se",
      "produjo",
      "el",
      "22",
      "de",
      "febrero",
      "de",
      "2012",
      ",",
      "provocando",
      "la",
      "muerte",
      "de",
      "51",
      "personas",
      "y",
      "lesiones",
      "a",
      "702",
      "personas",
      "."
    ],
    [
      "El",
      "segundo",
      "se",
      "produjo",
      "el",
      "13",
      "de",
      "junio",
      "de",
      "2013",
      ",",
      "provocando",
      "la",
      "muerte",
      "de",
      "3",
      "personas",
      "y",
      "lesiones",
      "a",
      "315",
      "personas",
      "."
    ],
    [
      "El",
      "tercero",
      "se",
      "produjo",
      "el",
      "19",
      "de",
      "octubre",
      "de",
      "2013",
      ",",
      "provocando",
      "lesiones",
      "a",
      "105",
      "personas",
      "."
    ]
  ],
  "deprel": [
    [
      [
        0,
        0
      ],
      [
        0,
        4
      ],
      "nsubj"
    ],
    [
      [
        0,
        1
      ],
      [
        0,
        2
      ],
      "case"
    ],
    [
      [
        0,
        2
      ],
      [
        0,
        0
      ],
      "nmod"
    ],
    [
      [
        0,
        3
      ],
      [
        0,
        4
      ],
      "obj"
    ],
    [
      [
        0,
        4
      ],
      [
        0,
        -1
      ],
      "root"
    ],
    [
      [
        0,
        5
      ],
      [
        0,
        7
      ],
      "case"
    ],
    [
      [
        0,
        6
      ],
      [
        0,
        7
      ],
      "det"
    ],
    [
      [
        0,
        7
      ],
      [
        0,
        4
      ],
      "obl"
    ],
    [
      [
        0,
        8
      ],
      [
        0,
        7
      ],
      "appos"
    ],
    [
      [
        0,
        9
      ],
      [
        0,
        4
      ],
      "punct"
    ],
    [
      [
        1,
        0
      ],
      [
        1,
        2
      ],
      "det"
    ],
    [
      [
        1,
        1
      ],
      [
        1,
        2
      ],
      "amod"
    ],
    [
      [
        1,
        2
      ],
      [
        1,
        4
      ],
      "nsubj"
    ],
    [
      [
        1,
        3
      ],
      [
        1,
        4
      ],
      "obj"
    ],
    [
      [
        1,
        4
      ],
      [
        1,
        -1
      ],
      "root"
    ],
    [
      [
        1,
        5
      ],
      [
        1,
        6
      ],
      "det"
    ],
    [
      [
        1,
        6
      ],
      [
        1,
        4
      ],
      "obl"
    ],
    [
      [
        1,
        7
      ],
      [
        1,
        8
      ],
      "case"
    ],
    [
      [
        1,
        8
      ],
      [
        1,
        6
      ],
      "compound"
    ],
    [
      [
        1,
        9
      ],
      [
        1,
        10
      ],
      "case"
    ],
    [
      [
        1,
        10
      ],
      [
        1,
        6
      ],
      "compound"
    ],
    [
      [
        1,
        11
      ],
      [
        1,
        12
      ],
      "punct"
    ],
    [
      [
        1,
        12
      ],
      [
        1,
        4
      ],
      "advcl"
    ],
    [
      [
        1,
        13
      ],
      [
        1,
        14
      ],
      "det"
    ],
    [
      [
        1,
        14
      ],
      [
        1,
        12
      ],
      "obj"
    ],
    [
      [
        1,
        15
      ],
      [
        1,
        17
      ],
      "case"
    ],
    [
      [
        1,
        16
      ],
      [
        1,
        17
      ],
      "nummod"
    ],
    [
      [
        1,
        17
      ],
      [
        1,
        14
      ],
      "nmod"
    ],
    [
      [
        1,
        18
      ],
      [
        1,
        19
      ],
      "cc"
    ],
    [
      [
        1,
        19
      ],
      [
        1,
        14
      ],
      "conj"
    ],
    [
      [
        1,
        20
      ],
      [
        1,
        22
      ],
      "case"
    ],
    [
      [
        1,
        21
      ],
      [
        1,
        22
      ],
      "nummod"
    ],
    [
      [
        1,
        22
      ],
      [
        1,
        19
      ],
      "nmod"
    ],
    [
      [
        1,
        23
      ],
      [
        1,
        4
      ],
      "punct"
    ],
    [
      [
        2,
        0
      ],
      [
        2,
        1
      ],
      "det"
    ],
    [
      [
        2,
        1
      ],
      [
        2,
        3
      ],
      "nsubj"
    ],
    [
      [
        2,
        2
      ],
      [
        2,
        3
      ],
      "obj"
    ],
    [
      [
        2,
        3
      ],
      [
        2,
        -1
      ],
      "root"
    ],
    [
      [
        2,
        4
      ],
      [
        2,
        5
      ],
      "det"
    ],
    [
      [
        2,
        5
      ],
      [
        2,
        3
      ],
      "obl"
    ],
    [
      [
        2,
        6
      ],
      [
        2,
        7
      ],
      "case"
    ],
    [
      [
        2,
        7
      ],
      [
        2,
        5
      ],
      "compound"
    ],
    [
      [
        2,
        8
      ],
      [
        2,
        9
      ],
      "case"
    ],
    [
      [
        2,
        9
      ],
      [
        2,
        5
      ],
      "compound"
    ],
    [
      [
        2,
        10
      ],
      [
        2,
        11
      ],
      "punct"
    ],
    [
      [
        2,
        11
      ],
      [
        2,
        3
      ],
      "advcl"
    ],
    [
      [
        2,
        12
      ],
      [
        2,
        13
      ],
      "det"
    ],
    [
      [
        2,
        13
      ],
      [
        2,
        11
      ],
      "obj"
    ],
    [
      [
        2,
        14
      ],
      [
        2,
        16
      ],
      "case"
    ],
    [
      [
        2,
        15
      ],
      [
        2,
        16
      ],
      "nummod"
    ],
    [
      [
        2,
        16
      ],
      [
        2,
        13
      ],
      "nmod"
    ],
    [
      [
        2,
        17
      ],
      [
        2,
        18
      ],
      "cc"
    ],
    [
      [
        2,
        18
      ],
      [
        2,
        13
      ],
      "conj"
    ],
    [
      [
        2,
        19
      ],
      [
        2,
        21
      ],
      "case"
    ],
    [
      [
        2,
        20
      ],
      [
        2,
        21
      ],
      "nummod"
    ],
    [
      [
        2,
        21
      ],
      [
        2,
        18
      ],
      "nmod"
    ],
    [
      [
        2,
        22
      ],
      [
        2,
        3
      ],
      "punct"
    ],
    [
      [
        3,
        0
      ],
      [
        3,
        1
      ],
      "det"
    ],
    [
      [
        3,
        1
      ],
      [
        3,
        3
      ],
      "nsubj"
    ],
    [
      [
        3,
        2
      ],
      [
        3,
        3
      ],
      "obj"
    ],
    [
      [
        3,
        3
      ],
      [
        3,
        -1
      ],
      "root"
    ],
    [
      [
        3,
        4
      ],
      [
        3,
        5
      ],
      "det"
    ],
    [
      [
        3,
        5
      ],
      [
        3,
        3
      ],
      "obl"
    ],
    [
      [
        3,
        6
      ],
      [
        3,
        7
      ],
      "case"
    ],
    [
      [
        3,
        7
      ],
      [
        3,
        5
      ],
      "compound"
    ],
    [
      [
        3,
        8
      ],
      [
        3,
        9
      ],
      "case"
    ],
    [
      [
        3,
        9
      ],
      [
        3,
        5
      ],
      "compound"
    ],
    [
      [
        3,
        10
      ],
      [
        3,
        11
      ],
      "punct"
    ],
    [
      [
        3,
        11
      ],
      [
        3,
        3
      ],
      "advcl"
    ],
    [
      [
        3,
        12
      ],
      [
        3,
        11
      ],
      "obj"
    ],
    [
      [
        3,
        13
      ],
      [
        3,
        15
      ],
      "case"
    ],
    [
      [
        3,
        14
      ],
      [
        3,
        15
      ],
      "nummod"
    ],
    [
      [
        3,
        15
      ],
      [
        3,
        11
      ],
      "obj"
    ],
    [
      [
        3,
        16
      ],
      [
        3,
        3
      ],
      "punct"
    ]
  ]
}